apsbits/__init__.py
apsbits/_version.py
apsbits/py.typed
apsbits/api/__init__.py
apsbits/api/create_new_instrument.py
apsbits/api/delete_instrument.py
apsbits/api/run_instrument.py
apsbits/configs/logging.yml
apsbits/core/__init__.py
apsbits/core/best_effort_init.py
apsbits/core/catalog_init.py
apsbits/core/instrument_init.py
apsbits/core/run_engine_init.py
apsbits/demo_instrument/README.md
apsbits/demo_instrument/__init__.py
apsbits/demo_instrument/startup.py
apsbits/demo_instrument/callbacks/__init__.py
apsbits/demo_instrument/callbacks/demo_nexus_callback.py
apsbits/demo_instrument/callbacks/demo_spec_callback.py
apsbits/demo_instrument/configs/__init__.py
apsbits/demo_instrument/configs/devices.yml
apsbits/demo_instrument/configs/devices_aps_only.yml
apsbits/demo_instrument/configs/extra_logging.yml
apsbits/demo_instrument/configs/iconfig.yml
apsbits/demo_instrument/devices/__init__.py
apsbits/demo_instrument/plans/__init__.py
apsbits/demo_instrument/plans/sim_plans.py
apsbits/demo_instrument/qserver/qs-config.yml
apsbits/demo_instrument/qserver/user_group_permissions.yaml
apsbits/demo_instrument/suspenders/__init__.py
apsbits/demo_instrument/utils/__init__.py
apsbits/demo_scripts/qs_host.sh
apsbits/tests/__init__.py
apsbits/tests/conftest.py
apsbits/tests/test_catalog_init.py
apsbits/tests/test_config.py
apsbits/tests/test_controls_setup.py
apsbits/tests/test_delete_instrument.py
apsbits/tests/test_device_factories.py
apsbits/tests/test_general.py
apsbits/tests/test_make_devices.py
apsbits/tests/test_run_instrument.py
apsbits/tests/test_stored_dict.py
apsbits/utils/__init__.py
apsbits/utils/aps_functions.py
apsbits/utils/baseline_setup.py
apsbits/utils/config_loaders.py
apsbits/utils/controls_setup.py
apsbits/utils/helper_functions.py
apsbits/utils/logging_setup.py
apsbits/utils/metadata.py
apsbits/utils/sim_creator.py
apsbits/utils/stored_dict.py
apsbits-2.0.1.dist-info/licenses/LICENSE
apsbits-2.0.1.dist-info/METADATA
apsbits-2.0.1.dist-info/WHEEL
apsbits-2.0.1.dist-info/entry_points.txt
apsbits-2.0.1.dist-info/top_level.txt
apsbits-2.0.1.dist-info/RECORD
