Metadata-Version: 2.4
Name: apsbits
Version: 2.0.1
Summary: Model of a Bluesky Data Acquisition Instrument in console, notebook, & queueserver.
Author-email: Eric Codrea <ecodrea@anl.gov>, Pete Jemian <prjemian+instrument@gmail.com>, Rafael Vescovi <rvescovi@anl.gov>
Maintainer-email: Eric Codrea <ecodrea@anl.gov>, Pete Jemian <prjemian+instrument@gmail.com>, Rafael Vescovi <rvescovi@anl.gov>
License-Expression: LicenseRef-ANL-Open-Source-License
Project-URL: Homepage, https://BCDA-APS.github.io/BITS/
Project-URL: Bug Tracker, https://github.com/BCDA-APS/BITS/issues
Keywords: bluesky,queueserver
Classifier: Development Status :: 4 - Beta
Classifier: Environment :: Console
Classifier: Intended Audience :: Science/Research
Classifier: Programming Language :: Python
Classifier: Programming Language :: Python :: 3
Classifier: Topic :: Utilities
Requires-Python: >=3.11
License-File: LICENSE
Requires-Dist: apstools
Requires-Dist: bluesky-queueserver>=0.0.22
Requires-Dist: bluesky-queueserver-api
Requires-Dist: bluesky-tiled-plugins
Requires-Dist: bluesky-widgets
Requires-Dist: bluesky
Requires-Dist: caproto
Requires-Dist: databroker==1.2.5
Requires-Dist: guarneri>=0.4.0
Requires-Dist: ipython
Requires-Dist: jupyterlab
Requires-Dist: matplotlib
Requires-Dist: ophyd-async
Requires-Dist: ophyd-registry
Requires-Dist: ophyd
Requires-Dist: PyQt5>5.15
Requires-Dist: pyRestTable
Requires-Dist: pysumreg
Requires-Dist: qtpy
Requires-Dist: tiled[all]
Requires-Dist: tomli-w
Requires-Dist: tomli
Provides-Extra: dev
Requires-Dist: build; extra == "dev"
Requires-Dist: isort; extra == "dev"
Requires-Dist: mypy; extra == "dev"
Requires-Dist: pre-commit; extra == "dev"
Requires-Dist: pytest; extra == "dev"
Requires-Dist: pytest-mock; extra == "dev"
Requires-Dist: ruff; extra == "dev"
Provides-Extra: doc
Requires-Dist: babel; extra == "doc"
Requires-Dist: ipykernel; extra == "doc"
Requires-Dist: jinja2; extra == "doc"
Requires-Dist: markupsafe; extra == "doc"
Requires-Dist: myst_parser; extra == "doc"
Requires-Dist: nbsphinx; extra == "doc"
Requires-Dist: pydata-sphinx-theme; extra == "doc"
Requires-Dist: pygments-ipython-console; extra == "doc"
Requires-Dist: pygments; extra == "doc"
Requires-Dist: sphinx-design; extra == "doc"
Requires-Dist: sphinx-tabs; extra == "doc"
Requires-Dist: sphinx; extra == "doc"
Requires-Dist: graphviz; extra == "doc"
Requires-Dist: dot; extra == "doc"
Requires-Dist: tomli-w; extra == "doc"
Provides-Extra: all
Requires-Dist: apsbits[dev,doc]; extra == "all"
Dynamic: license-file
